physicsx/component_protocol/__init__.py
physicsx/component_protocol/_protocol.py
physicsx/component_protocol/_validation.py
physicsx/component_protocol/py.typed
physicsx_component_protocol-0.1.0.dist-info/WHEEL
physicsx_component_protocol-0.1.0.dist-info/METADATA
physicsx_component_protocol-0.1.0.dist-info/RECORD
