Metadata-Version: 2.3
Name: physicsx-component-protocol
Version: 0.1.0
Summary: PXC-001 Component Protocol implementation
Requires-Dist: pydantic~=2.7
Requires-Dist: typeguard~=4.3
Requires-Python: >=3.10, <3.15
